fastmcp_agents/library/agent/documentation_maintainer/__init__.py
fastmcp_agents/library/agent/documentation_maintainer/agent.py
fastmcp_agents/library/agent/documentation_maintainer/esql_expert.py.disabled
fastmcp_agents/library/agent/documentation_maintainer/logging.py
fastmcp_agents/library/agent/documentation_maintainer/shared.py.disabled
fastmcp_agents_library_agent_documentation_maintainer-0.5.7.dist-info/WHEEL
fastmcp_agents_library_agent_documentation_maintainer-0.5.7.dist-info/entry_points.txt
fastmcp_agents_library_agent_documentation_maintainer-0.5.7.dist-info/METADATA
fastmcp_agents_library_agent_documentation_maintainer-0.5.7.dist-info/RECORD
