Metadata-Version: 2.3
Name: fastmcp-agents-library-agent-documentation-maintainer
Version: 0.5.7
Summary: An agent for maintaining documentation
Requires-Dist: fastmcp
Requires-Dist: fastmcp-agents-library-mcp
Requires-Dist: fastmcp-ai-agent-bridge-pydantic-ai>=0.1.0
Requires-Dist: gitpython>=3.1.44
Requires-Dist: pydantic>=2.11.7
Requires-Dist: pydantic-ai>=0.4.4
Requires-Python: >=3.13
